{
    "nixpkgs-dev": {
        "branch": "nixpkgs-unstable",
        "description": "Nix Packages collection",
        "homepage": "",
        "owner": "NixOS",
        "repo": "nixpkgs",
        "rev": "cbb95673926205f7a54af97ecfa32bc7be917603",
        "sha256": "1c8lcwm491icx96aimq0hh9kbvpbz7ds52f65j5ibffhf67ar3w9",
        "type": "tarball",
        "url": "https://github.com/NixOS/nixpkgs/archive/cbb95673926205f7a54af97ecfa32bc7be917603.tar.gz",
        "url_template": "https://github.com/<owner>/<repo>/archive/<rev>.tar.gz"
    },
    "test-stable": {
        "branch": "nixos-21.11",
        "description": "Nix Packages collection",
        "homepage": "",
        "owner": "NixOS",
        "repo": "nixpkgs",
        "rev": "2de556c4cd46a59e8ce2f85ee4dd400983213d45",
        "sha256": "18rhjpyj9p7ip49r14cahdzqxaipx4w9imib1303pifx8xk2vd33",
        "type": "tarball",
        "url": "https://github.com/NixOS/nixpkgs/archive/2de556c4cd46a59e8ce2f85ee4dd400983213d45.tar.gz",
        "url_template": "https://github.com/<owner>/<repo>/archive/<rev>.tar.gz"
    },
    "test-unstable": {
        "branch": "nixos-unstable",
        "description": "Nix Packages collection",
        "homepage": "",
        "owner": "NixOS",
        "repo": "nixpkgs",
        "rev": "b62ada430501de88dfbb08cea4eb98ead3a5e3e7",
        "sha256": "1ppaixbncqyvy2ixskwvzggjsw20j77iy3aqyk4749dvkx0ml27f",
        "type": "tarball",
        "url": "https://github.com/NixOS/nixpkgs/archive/b62ada430501de88dfbb08cea4eb98ead3a5e3e7.tar.gz",
        "url_template": "https://github.com/<owner>/<repo>/archive/<rev>.tar.gz"
    }
}
